nash_mpqp.py
nash_mpqp-0.1.0.dist-info/licenses/LICENSE
nash_mpqp-0.1.0.dist-info/METADATA
nash_mpqp-0.1.0.dist-info/WHEEL
nash_mpqp-0.1.0.dist-info/top_level.txt
nash_mpqp-0.1.0.dist-info/RECORD
