Metadata-Version: 2.4
Name: nash-mpqp
Version: 0.1.0
Summary: nash-mpqp - A Python package for solving parametric generalized Nash equilibrium (GNE) problems with quadratic objectives and coupled linear inequality constraints in explicit form.
Author-email: Alberto Bemporad <alberto.bemporad@imtlucca.it>, Sophie Hall <shall@control.ee.ethz.ch>
Project-URL: Homepage, https://github.com/bemporad/nash-mpqp
Keywords: generalized nash equilibrium problems,game theory,multiparametric programming,model predictive control
Classifier: Programming Language :: Python :: 3
Classifier: License :: OSI Approved :: Apache Software License
Classifier: Operating System :: OS Independent
Requires-Python: >=3.9
License-File: LICENSE
Requires-Dist: numpy
Requires-Dist: matplotlib
Requires-Dist: pdaqp
Requires-Dist: daqp
Requires-Dist: joblib
Requires-Dist: scipy
Requires-Dist: pypoman
Requires-Dist: dill
Requires-Dist: tqdm
Dynamic: license-file
